{
  "name": "Steadfast Heart",
  "passiveStats": [
    { "name": "Item:Steadfast Heart:MaxHp", "effectType": "Buff", "crowdControlType": "None", "affectedStat": "MaxHp", "modifierType": "Flat", "value": 250, "durationMs": 60000, "remainingMs": 60000, "tickIntervalMs": 0, "tickTimerMs": 0, "damageType": "True" },
    { "name": "Item:Steadfast Heart:DamageReduction", "effectType": "DamageReduction", "crowdControlType": "None", "affectedStat": "DamageReduction", "modifierType": "Flat", "value": 0.15, "durationMs": 60000, "remainingMs": 60000, "tickIntervalMs": 0, "tickTimerMs": 0, "damageType": "True" },
    { "name": "Item:Steadfast Heart:CritChance", "effectType": "CritChanceBonus", "crowdControlType": "None", "affectedStat": "CritChance", "modifierType": "Flat", "value": 0.2, "durationMs": 60000, "remainingMs": 60000, "tickIntervalMs": 0, "tickTimerMs": 0, "damageType": "True" },
    { "name": "Item:Steadfast Heart:DamageReduction", "effectType": "DamageReduction", "crowdControlType": "None", "affectedStat": "DamageReduction", "modifierType": "Flat", "value": 0.05, "durationMs": 60000, "remainingMs": 60000, "tickIntervalMs": 0, "tickTimerMs": 0, "damageType": "True" },
    { "name": "Item:Steadfast Heart:Armor", "effectType": "BonusArmor", "crowdControlType": "None", "affectedStat": "Armor", "modifierType": "Flat", "value": 20, "durationMs": 60000, "remainingMs": 60000, "tickIntervalMs": 0, "tickTimerMs": 0, "damageType": "True" }
  ],
  "triggeredEffects": []
}
