{
  "name": "Vayne's Chromablades",
  "passiveStats": [
    { "name": "Item:Vayne's Chromablades:AttackSpeed", "effectType": "BonusAttackSpeed", "crowdControlType": "None", "affectedStat": "AttackSpeed", "modifierType": "Percent", "value": 0.5, "durationMs": 60000, "remainingMs": 60000, "tickIntervalMs": 0, "tickTimerMs": 0, "damageType": "True" },
    { "name": "Item:Vayne's Chromablades:AttackDamage", "effectType": "BonusAttackDamage", "crowdControlType": "None", "affectedStat": "AttackDamage", "modifierType": "Percent", "value": 0.3, "durationMs": 60000, "remainingMs": 60000, "tickIntervalMs": 0, "tickTimerMs": 0, "damageType": "True" }
  ],
  "triggeredEffects": []
}
